jtech/__init__.py
jtech/__main__.py
jtech/architecture/__init__.py
jtech/architecture/clean_architecture_generator.py
jtech/architecture/cqrs_architecture_generator.py
jtech/clean_generators/__init__.py
jtech/clean_generators/adapters/__init__.py
jtech/clean_generators/adapters/clean_adapter_generator.py
jtech/clean_generators/configs/__init__.py
jtech/clean_generators/configs/clean_config_generator.py
jtech/clean_generators/controllers/__init__.py
jtech/clean_generators/controllers/clean_controller_generator.py
jtech/clean_generators/domains/__init__.py
jtech/clean_generators/domains/clean_domain_generator.py
jtech/clean_generators/entities/__init__.py
jtech/clean_generators/entities/clean_entity_default_generator.py
jtech/clean_generators/entities/clean_entity_jpa2_generator.py
jtech/clean_generators/entities/clean_entity_jpa3_generator.py
jtech/clean_generators/entities/clean_entity_mongo_generator.py
jtech/clean_generators/exceptions/__init__.py
jtech/clean_generators/exceptions/clean_api_error_generator.py
jtech/clean_generators/exceptions/clean_api_sub_error_generator.py
jtech/clean_generators/exceptions/clean_api_validation_error_generator.py
jtech/clean_generators/ports/__init__.py
jtech/clean_generators/ports/clean_input_gateway_generator.py
jtech/clean_generators/ports/clean_output_gateway_generator.py
jtech/clean_generators/protocols/__init__.py
jtech/clean_generators/protocols/clean_request_generator.py
jtech/clean_generators/protocols/clean_response_generator.py
jtech/clean_generators/repositories/__init__.py
jtech/clean_generators/repositories/clean_repository_default_generator.py
jtech/clean_generators/repositories/clean_repository_jpa_generator.py
jtech/clean_generators/repositories/clean_repository_mongo_generator.py
jtech/clean_generators/usecases/__init__.py
jtech/clean_generators/usecases/clean_usecase_generator.py
jtech/clean_generators/utils/__init__.py
jtech/clean_generators/utils/clean_gen_id_generator.py
jtech-1.0.11.dist-info/entry_points.txt
jtech-1.0.11.dist-info/WHEEL
jtech-1.0.11.dist-info/METADATA
jtech-1.0.11.dist-info/RECORD
