Metadata-Version: 2.1
Name: jtech
Version: 1.0.11
Summary: Jtech Project CLI
Author: Angelo Vicente Filho
Author-email: angelo.vicente@veolia.com
Requires-Python: >=3.10,<4.0
Classifier: Programming Language :: Python :: 3
Classifier: Programming Language :: Python :: 3.10
Requires-Dist: Jinja2 (==3.1.2)
Requires-Dist: MarkupSafe (==2.1.3)
Requires-Dist: bs4 (>=0.0.1,<0.0.2)
Requires-Dist: certifi (==2023.5.7)
Requires-Dist: charset-normalizer (==3.1.0)
Requires-Dist: click (==8.1.3)
Requires-Dist: colorama (==0.4.6)
Requires-Dist: idna (==3.4)
Requires-Dist: prompt-toolkit (==3.0.38)
Requires-Dist: pyfiglet (>=0.8.post1,<0.9)
Requires-Dist: pyqt5 (>=5.15.9,<6.0.0)
Requires-Dist: pyyaml (>=6.0,<7.0)
Requires-Dist: qdarkstyle (>=3.1,<4.0)
Requires-Dist: questionary (==1.10.0)
Requires-Dist: requests (==2.31.0)
Requires-Dist: ruamel-yaml (>=0.17.32,<0.18.0)
Requires-Dist: setuptools (>=68.0.0,<69.0.0)
Requires-Dist: textwrap3 (>=0.9.2,<0.10.0)
Requires-Dist: urllib3 (==1.26.4)
Requires-Dist: wcwidth (==0.2.6)
